pydantic_kitbash/__init__.py
pydantic_kitbash/_version.py
pydantic_kitbash/directives.py
pydantic_kitbash-1.0.0.dist-info/licenses/LICENSE
pydantic_kitbash-1.0.0.dist-info/METADATA
pydantic_kitbash-1.0.0.dist-info/WHEEL
pydantic_kitbash-1.0.0.dist-info/top_level.txt
pydantic_kitbash-1.0.0.dist-info/RECORD
